vlog/tmds_decode.v
// A decode module used for simulation to test the encoder
// By Liam Davey (3/3/2011)

`timescale 1ns / 1ps

module tmds_decode (
	input clk, input rst,
	input [9:0] q_in,
	output reg [7:0] d,
	output reg c0,
	output reg c1,
	output reg de,
	output reg signed [7:0] cnt);

	reg [9:0] s1_q_in;
	wire [7:0] d_q;
	reg c0_1, c1_1, de_1;
	genvar i;
	
	wire signed [7:0] n1_q_in = q_in[9] + q_in[8] + q_in[7] + q_in[6] + q_in[5] + q_in[4] + q_in[3] + q_in[2] + q_in[1] + q_in[0];
	reg signed [7:0] q_in_disparity;
	
	// decode stage 2, XNOR or XOR depending on bit 8
	assign d_q[0] = s1_q_in[0];
	for (i = 1; i < 8; i = i + 1) begin : decode_loop
		assign d_q[i] = (s1_q_in[8]) ? (s1_q_in[i] ^ s1_q_in[i - 1]) : ~(s1_q_in[i] ^ s1_q_in[i - 1]);
	end
	
	always @ (posedge clk) begin
		if (rst) begin
			cnt <= 0;
		end else begin
			case(q_in)
				10'b1101010100 : {de_1, c0_1, c1_1} <= 3'b000;
				10'b0010101011 : {de_1, c0_1, c1_1} <= 3'b001;
				10'b0101010100 : {de_1, c0_1, c1_1} <= 3'b010;
				10'b1010101011 : {de_1, c0_1, c1_1} <= 3'b011;
				default : {de_1, c0_1, c1_1} <= 3'b100;
			endcase
			
			// decode stage 1, invert data bits if bit 9 set
			s1_q_in[9:8] <= q_in[9:8];
			s1_q_in[7:0] <= (q_in[9]) ? (~q_in[7:0]) : (q_in[7:0]);
			
			// output results from stage 2
			d <= d_q;
			
			de <= de_1;
			c0 <= c0_1;
			c1 <= c1_1;
			
			// update cnt, the disparity count
			q_in_disparity = {n1_q_in, 1'b0} - 8'd10;
			cnt <= cnt + q_in_disparity;
		end
	end
endmodule

vlog/tmds_encode.v
////////////////////////////////////////////////////////////////////////
// DVI encoder module
// ==================
//
// By Liam Davey (03/03/11)
//
// Encodes either the 8 bit pixel data 'd' or control signals 'c0' and
// 'c1', depending on the value of 'de' (data enable), to a 10 bit value
// q_out. The 10-bit 'q_out' value is suitable for serialization to send
// over the DVI cable (using Transition Minimized Differential
// Signalling (TMDS)).
//
// Created based on Figure 3-5 of the DVI Specification 1.0, available
// from http://www.ddwg.org/lib/dvi_10.pdf
//
////////////////////////////////////////////////////////////////////////

/*

the encoding algorithm tries to on average send the same number of
ones as zeroes so no DC shift occurs on the differential pair.
it achieves this by selectively inverting the 9 bit output of the
previous stage (q_m). the tenth bit is used to signal whether or
not this inversion occurred.

if the current disparity is 0 (same number of total ones and zeroes
sent so far) then it does not really matter whether we invert
q_m[7:0] or not, as either way the disparity will not improve.
likewise if q_m[7:0] has an equal number of ones and zeroes then
whether we invert or not does not affect the disparity.

in either case the algorithm in the specification inverts the lower
8 bits if the 9th bit (XOR/XNOR flag) is 0, so that the top two
will be '10' - not affecting the disparity.
alternatively if the 9th bit is 1 no inversion will take place so
that the top two bits are '01' - again not affecting disparity.

i think there is room for improvement in the specified algorithm 
here. it would be possible (without modifying the decode algorithm)
to make the 9th and 10th bits '11' or '00' based on the number of
ones in the lower 8 bits to improve the disparity (and
inadvertently reduce the number of transitions).

if however the disparity is not 0 and there is not an equal number
of ones and zeroes in q_m[7:0], then we should decide whether or
not to invert the bits.
if we have more total ones sent and there are more ones in q_m[7:0]
than zeroes, q_m[7:0] should be inverted.
likewise if more total zeroes have been sent and there are more
zeroes than ones in q_m[7:0], we should also invert.
in all other cases, do not invert.

*/

module tmds_encode (
	input clk,				// clock signal
	input rst,				// reset signal
	input [7:0] d,			// input 8 bit pixel data
	input de,				// data enable (1 = data, 0 = control)
	input c0,				// control signal 0
	input c1,				// control signal 1
	output reg [9:0] q_out	// the encoded 10 bit value to output LSB first
									// on the differential channel
	);
	
	// copies of data for stage 1 so that the data is aligned
	// for the pipeline stage
	// i.e. so that 'd' is available next clock cycle even though
	// the input 'd' has changed
	reg [7:0] s1_d;
	reg s1_de, s1_c0, s1_c1;
	
	// copies of data for stage 2
	reg s2_de, s2_c0, s2_c1;
	reg [8:0] s2_q;
	
	// the transition minimized 9-bit output of stage 1
	wire [8:0] s1_q;
	
	// count of ones in data for stage 1
	reg [3:0] s1_n1;
	
	// count of ones in data for stage 2 (not a copy of s1_n1)
	reg [3:0] s2_n1;
	
	// disparity count (difference between total number of ones sent and
	// total number of zeroes sent). will be negative (MSB set) if more
	// zeroes than ones have been sent.
	reg signed [4:0] s2_cnt;// s2_cnt_prev;
	reg signed [4:0] s2_flag_bits_disparity, s2_q_disparity;

	// 8b -> 9b encoding
	// creates a transition minimized version of the input data.
	// asynchronous, the output q_m changes as soon as inputs s1_n1 or
	// s1_d1 from stage 1 change.
	// if this proves to be too slow could implement as another pipeline
	// stage instead (q_m as a register).

	wire use_xnor = (s1_n1 > 4'h4) || ((s1_n1 == 4'h4) && (s1_d[0] == 1'b0));
	assign s1_q[0] = s1_d[0];
	
	genvar i;
	for (i = 1; i < 8; i = i + 1) begin : xnor_loop
		assign s1_q[i] = (use_xnor) ? (~(s1_q[i - 1] ^ s1_d[i])) : (s1_q[i - 1] ^ s1_d[i]);
	end
	assign s1_q[8] = ~use_xnor;	// bit 9 indicates whether XNOR or XOR was used


	// decide whether we need to invert the lower 8 bits or not
	wire data_balanced = (s2_n1 == 4);			// true if data has 4 ones and 4 zeroes
	wire data_has_more_zeroes = (s2_n1 < 4);	// true if data has more zeroes than ones
	wire data_has_more_ones = (s2_n1 > 4);		// true if data has more ones than zeroes
	wire disparity_zero = (s2_cnt == 0);			// true if we have sent the same number of ones as zeroes
	wire need_more_ones = s2_cnt[4];					// true if we need to send more ones to balance disparity
	
	// check if inverting the lower 8 bits would improve disparity
	// (this neglects the case where disparity is already 0, in which case
	// whether to invert or not is decided differently)
	assign inversion_needed = (need_more_ones && data_has_more_zeroes) | 
		((~need_more_ones) && data_has_more_ones);

	// if disparity is zero or the data has equal number of ones and zeroes
	// then invert based on s2_q_m[8], otherwise based on the above decision
	assign invert_data = (disparity_zero | data_balanced) ? 
		(~s2_q[8]) : (inversion_needed);
	
	// how many more ones than zeroes are in the 8 data bits
	wire signed [4:0] s2_data_disparity = {s2_n1, 1'b0} - 8;
	
	// check if DE is low, signalling that we are sending control data
	// rather than pixel data
	always @ (posedge clk or posedge rst) begin
		if (rst) begin
			s2_cnt <= 0;
		end else begin
			// pipeline stage 1
			// count the number of one bits in d[7:0]
			s1_n1 <= d[7] + d[6] + d[5] + d[4] + d[3] + d[2] + d[1] + d[0];
			s1_d <= d;	// copy registers for use with later stages
			s1_de <= de;
			s1_c0 <= c0;
			s1_c1 <= c1;
			
			// find the number of ones in s1_q[7:0]
			s2_n1 <= 
				s1_q[7] + s1_q[6] + s1_q[5] + s1_q[4] + 
				s1_q[3] + s1_q[2] + s1_q[1] + s1_q[0];
			s2_de <= s1_de;
			s2_c0 <= s1_c0;
			s2_c1 <= s1_c1;
			s2_q <= s1_q;
			
			if (s2_de == 1'b0) begin
				// use a simple lookup table to create the 10-bit code to output
				// note that these are reversed compared to the specification
				// document as it used q_out[0:9] rather than q_out[9:0]
				case ({s2_c1, s2_c0})
					2'b00   : q_out <= 10'b1101010100;
					2'b01   : q_out <= 10'b0010101011;
					2'b10   : q_out <= 10'b0101010100;
					default : q_out <= 10'b1010101011;
				endcase
				s2_cnt <= 0;

			end else begin
				q_out[9] <= invert_data;
				q_out[8] <= s2_q[8];
				q_out[7:0] <= (invert_data) ? (~s2_q[7:0]) : (s2_q[7:0]);
				s2_flag_bits_disparity = {invert_data && s2_q[8], 1'b0} - {~(invert_data || s2_q[8]), 1'b0};
				s2_q_disparity = (invert_data) ? (s2_flag_bits_disparity - s2_data_disparity) : (s2_flag_bits_disparity + s2_data_disparity);
				//s2_cnt_prev <= s2_cnt;
				s2_cnt <= s2_cnt + s2_q_disparity;
			end
		end
	end
endmodule

vlog/tmds_encode_tb.v
`timescale 1ns / 1ps
`include "tmds_encode.v"
`include "tmds_decode.v"

module tmds_encode_tb;

	// Inputs
	reg clk;
	reg rst;
	reg [7:0] d;
	reg de;
	reg c0;
	reg c1;

	// Outputs
	wire [9:0] q_out;
	
	wire [7:0] d_out;
	wire de_out, c0_out, c1_out;
	wire signed [7:0] count_out;

	// Instantiate the Unit Under Test (UUT)
	tmds_encode uut (
		.clk(clk), 
		.rst(rst), 
		.d(d), 
		.de(de), 
		.c0(c0), 
		.c1(c1), 
		.q_out(q_out)
	);
	
	// inputs of decode module
	tmds_decode u_tmds_decode (
		.clk(clk),
		.rst(rst),
		.q_in(q_out),
		.d(d_out),
		.de(de_out),
		.c0(c0_out),
		.c1(c1_out),
		.cnt(count_out));
	
	always begin
		#5 clk = ~clk;
	end
	
	reg rand_in_enable;
	reg [7:0] delay_count, delay_length, delayed_d_in;
	reg [7:0] d_delay [7:0];
	
	always @ (posedge clk) begin
		if (de) begin
			if (rand_in_enable) begin
				d <= $random % 256;
				case (delay_length)
					8'd2 : delayed_d_in = d_delay[0];
					8'd3 : delayed_d_in = d_delay[1];
					8'd4 : delayed_d_in = d_delay[2];
					8'd5 : delayed_d_in = d_delay[3];
					8'd6 : delayed_d_in = d_delay[4];
					8'd7 : delayed_d_in = d_delay[5];
					8'd8 : delayed_d_in = d_delay[6];
					8'd9 : delayed_d_in = d_delay[7];
					default : delayed_d_in = 8'hxx;
				endcase
				if (d_out != delayed_d_in) begin
					$display ("error: dout (%x) != din (%x)", d_out, delayed_d_in);
				end
			end else begin	
				d <= (delay_count == 8'd0) ? 8'h5a : 8'h00;
				delay_count <= delay_count + 1;
				if (d_out == 8'h5a) begin
					$display ("received sync byte after delay of %d", delay_count);
					delay_length <= delay_count;
					rand_in_enable <= 1'b1;
				end
			end
			d_delay[0] <= d;
			d_delay[1] <= d_delay[0];
			d_delay[2] <= d_delay[1];
			d_delay[3] <= d_delay[2];
			d_delay[4] <= d_delay[3];
			d_delay[5] <= d_delay[4];
			d_delay[6] <= d_delay[5];
			d_delay[7] <= d_delay[6];
			
			if (count_out < -10 || count_out > 10) begin
				$display("warning: large disparity on differential line detected (%d)", count_out);
			end
		end
	end
	
			

	initial begin
		$monitor ("d_in=%x, d_out=%x, q_out=%x, count_out=%d", d, d_out, q_out, count_out);
		$dumpfile("tmds_encode_tb.vcd");
		$dumpvars;
		// Initialize Inputs
		clk = 0;
		rst = 0;
		d = 0;
		de = 0;
		c0 = 0;
		c1 = 0;
		rand_in_enable = 1'b0;
		delay_count = 0;
		delay_length = 0;
		
		// reset pulse
		#40 rst = 1'b1;
		#80 rst = 1'b0;
        
		// Add stimulus here
		
		#120 de = 1'b1;
		
		#1000 $finish;

	end
      
endmodule

vlog/tmds_encode_tb.vcd
$date
	Wed Sep 28 09:22:27 2011
$end
$version
	Icarus Verilog
$end
$timescale
	1ps
$end
$scope module tmds_encode_tb $end
$var wire 1 ! c0_out $end
$var wire 1 " c1_out $end
$var wire 8 # count_out [7:0] $end
$var wire 8 $ d_out [7:0] $end
$var wire 1 % de_out $end
$var wire 10 & q_out [9:0] $end
$var reg 1 ' c0 $end
$var reg 1 ( c1 $end
$var reg 1 ) clk $end
$var reg 8 * d [7:0] $end
$var reg 1 + de $end
$var reg 8 , delay_count [7:0] $end
$var reg 8 - delay_length [7:0] $end
$var reg 8 . delayed_d_in [7:0] $end
$var reg 1 / rand_in_enable $end
$var reg 1 0 rst $end
$scope module uut $end
$var wire 1 1 c0 $end
$var wire 1 2 c1 $end
$var wire 1 3 clk $end
$var wire 8 4 d [7:0] $end
$var wire 1 5 data_balanced $end
$var wire 1 6 data_has_more_ones $end
$var wire 1 7 data_has_more_zeroes $end
$var wire 1 8 de $end
$var wire 1 9 disparity_zero $end
$var wire 1 : inversion_needed $end
$var wire 1 ; invert_data $end
$var wire 1 < need_more_ones $end
$var wire 1 = rst $end
$var wire 9 > s1_q [8:0] $end
$var wire 5 ? s2_data_disparity [4:0] $end
$var wire 1 @ use_xnor $end
$var reg 10 A q_out [9:0] $end
$var reg 1 B s1_c0 $end
$var reg 1 C s1_c1 $end
$var reg 8 D s1_d [7:0] $end
$var reg 1 E s1_de $end
$var reg 4 F s1_n1 [3:0] $end
$var reg 1 G s2_c0 $end
$var reg 1 H s2_c1 $end
$var reg 5 I s2_cnt [4:0] $end
$var reg 1 J s2_de $end
$var reg 5 K s2_flag_bits_disparity [4:0] $end
$var reg 4 L s2_n1 [3:0] $end
$var reg 9 M s2_q [8:0] $end
$var reg 5 N s2_q_disparity [4:0] $end
$scope begin xnor_loop[1] $end
$upscope $end
$scope begin xnor_loop[2] $end
$upscope $end
$scope begin xnor_loop[3] $end
$upscope $end
$scope begin xnor_loop[4] $end
$upscope $end
$scope begin xnor_loop[5] $end
$upscope $end
$scope begin xnor_loop[6] $end
$upscope $end
$scope begin xnor_loop[7] $end
$upscope $end
$upscope $end
$scope module u_tmds_decode $end
$var wire 1 3 clk $end
$var wire 8 O d_q [7:0] $end
$var wire 8 P n1_q_in [7:0] $end
$var wire 10 Q q_in [9:0] $end
$var wire 1 = rst $end
$var reg 1 R c0 $end
$var reg 1 S c0_1 $end
$var reg 1 T c1 $end
$var reg 1 U c1_1 $end
$var reg 8 V cnt [7:0] $end
$var reg 8 W d [7:0] $end
$var reg 1 X de $end
$var reg 1 Y de_1 $end
$var reg 8 Z q_in_disparity [7:0] $end
$var reg 10 [ s1_q_in [9:0] $end
$scope begin decode_loop[1] $end
$upscope $end
$scope begin decode_loop[2] $end
$upscope $end
$scope begin decode_loop[3] $end
$upscope $end
$scope begin decode_loop[4] $end
$upscope $end
$scope begin decode_loop[5] $end
$upscope $end
$scope begin decode_loop[6] $end
$upscope $end
$scope begin decode_loop[7] $end
$upscope $end
$upscope $end
$upscope $end
$enddefinitions $end
#0
$dumpvars
bx [
bx Z
xY
xX
bx W
bx V
xU
xT
xS
xR
bx Q
bx P
bx O
bx N
bx M
bx L
bx K
xJ
bx I
xH
xG
bx F
xE
bx D
xC
xB
bx A
x@
bx ?
bx >
0=
x<
x;
x:
x9
08
x7
x6
x5
b0 4
03
02
01
00
0/
bx .
b0 -
b0 ,
0+
b0 *
0)
0(
0'
bx &
x%
bx $
bx #
x"
x!
$end
#5000
b100000000 >
0@
bx [
1Y
0S
0U
bx A
0C
0B
0E
b0 D
b0 F
1)
13
#10000
0)
03
#15000
b11000 ?
0T
0"
0R
0!
1X
1%
bx [
bx A
b100000000 M
0H
0G
0J
b0 L
05
17
06
1)
13
#20000
0)
03
#25000
0:
0;
0<
b101 P
bx [
b0 I
19
b1101010100 A
b1101010100 &
b1101010100 Q
1)
13
#30000
0)
03
#35000
b11111101 O
b1110101011 [
0Y
b0 Z
1)
13
#40000
0)
03
10
1=
#45000
b0 V
b0 #
1)
13
#50000
0)
03
#55000
1)
13
#60000
0)
03
#65000
1)
13
#70000
0)
03
#75000
1)
13
#80000
0)
03
#85000
1)
13
#90000
0)
03
#95000
1)
13
#100000
0)
03
#105000
1)
13
#110000
0)
03
#115000
1)
13
#120000
0)
03
00
0=
#125000
0X
0%
b11111101 W
b11111101 $
b1110101011 [
1)
13
#130000
0)
03
#135000
b1110101011 [
1)
13
#140000
0)
03
#145000
b1110101011 [
1)
13
#150000
0)
03
#155000
b1110101011 [
1)
13
#160000
0)
03
#165000
b1110101011 [
1)
13
#170000
0)
03
#175000
b1110101011 [
1)
13
#180000
0)
03
#185000
b1110101011 [
1)
13
#190000
0)
03
#195000
b1110101011 [
1)
13
#200000
0)
03
#205000
b1110101011 [
1)
13
#210000
0)
03
#215000
b1110101011 [
1)
13
#220000
0)
03
#225000
b1110101011 [
1)
13
#230000
0)
03
#235000
b1110101011 [
1)
13
#240000
0)
03
1+
18
#245000
b1110101011 [
b1 ,
b1011010 *
b1011010 4
1E
1)
13
#250000
0)
03
#255000
b10011100 >
1@
b10 ,
b0 *
b0 4
b1110101011 [
1J
b1011010 D
b100 F
1)
13
#260000
0)
03
#265000
1;
b100000000 >
0@
1<
b1 P
b0 ?
b1110101011 [
b11 ,
b11000 I
09
b100000000 A
b100000000 &
b100000000 Q
b10011100 M
b100 L
15
07
b0 D
b0 F
b11000 N
b0 K
1)
13
#270000
0)
03
#275000
1:
b0 O
b101 P
b11000 ?
b100 ,
b11111000 V
b11111000 #
b100000000 [
1Y
b1001100011 A
b1001100011 &
b1001100011 Q
b100000000 M
b0 L
05
17
b11111000 Z
b0 N
1)
13
#280000
0)
03
#285000
0;
0:
b1011010 O
0<
b1010 P
1X
1%
b0 W
b0 $
b1010011100 [
b101 ,
b10 I
b1111111111 &
b1111111111 Q
b1111111111 A
b0 Z
b1010 N
b10 K
1)
13
#290000
0)
03
#295000
1;
1:
b0 O
1<
b1 P
b110 ,
b10 V
b10 #
b1011010 W
b1011010 $
b1100000000 [
b11010 I
b100000000 A
b100000000 &
b100000000 Q
b1010 Z
b11000 N
b0 K
1)
13
#300000
0)
03
#305000
0;
0:
0<
b1010 P
b11111010 V
b11111010 #
b0 W
b0 $
b100000000 [
1/
b110 -
b111 ,
b100 I
b1111111111 A
b1111111111 &
b1111111111 Q
b11111000 Z
b1010 N
b10 K
1)
13
#310000
0)
03
#315000
1;
1:
1<
b1 P
b100100 *
b100100 4
b100 V
b100 #
b1100000000 [
b11100 I
b100000000 A
b100000000 &
b100000000 Q
b0 .
b1010 Z
b11000 N
b0 K
1)
13
#320000
0)
03
#325000
0;
0:
b100011100 >
0<
b1010 P
b11111100 V
b11111100 #
b100000000 [
b10000001 *
b10000001 4
b110 I
b1111111111 A
b1111111111 &
b1111111111 Q
b100100 D
b10 F
b11111000 Z
b1010 N
b10 K
1)
13
#330000
0)
03
#335000
1;
1:
1<
b1 P
b11110 ?
b101111111 >
b1001 *
b1001 4
b110 V
b110 #
b1100000000 [
b11110 I
b100000000 A
b100000000 &
b100000000 Q
b100011100 M
b11 L
b10000001 D
b1010 Z
b11000 N
b0 K
1)
13
#340000
0)
03
#345000
1;
b100000111 >
1:
0<
b111 P
b110 ?
b11111110 V
b11111110 #
b100000000 [
b1100011 *
b1100011 4
b10 I
b1111100011 A
b1111100011 &
b1111100011 Q
b101111111 M
b111 L
07
16
b1001 D
b11111000 Z
b100 N
b10 K
1)
13
#350000
0)
03
#355000
b100100 O
1;
b100100001 >
1:
1<
b11 P
b11110 ?
b1101 *
b1101 4
b10 V
b10 #
b1100011100 [
b11110 I
b1110000000 &
b1110000000 Q
b1110000000 A
b100000111 M
b11 L
17
06
b1100011 D
b100 F
b100 Z
b11100 N
1)
13
#360000
0)
03
#365000
0;
0:
b111111011 >
b10000001 O
0<
b111 P
b11100 ?
b11111110 V
b11111110 #
b100100 W
b100100 $
b1101111111 [
b10001101 *
b10001101 4
b10 I
b1111111000 &
b1111111000 Q
b1111111000 A
b100100001 M
b10 L
b1101 D
b11 F
b11111100 Z
b100 N
1)
13
#370000
0)
03
#375000
b1001 O
0;
b101111011 >
0:
1<
b11 P
b110 ?
b1100101 *
b1100101 4
b10 V
b10 #
b10000001 W
b10000001 $
b1100000111 [
b11110 I
b100100001 A
b100100001 &
b100100001 Q
b111111011 M
b111 L
07
16
b10001101 D
b100 F
b100100 .
b100 Z
b11100 N
b0 K
1)
13
#380000
0)
03
#385000
1;
1:
b1100011 O
b100100011 >
0<
b1000 P
b100 ?
b11111110 V
b11111110 #
b1001 W
b1001 $
b100100001 [
b10010 *
b10010 4
b100 I
b111111011 &
b111111011 Q
b111111011 A
b101111011 M
b110 L
b1100101 D
b11111100 Z
b10000001 .
b110 N
1)
13
#390000
0)
03
#395000
b1101 O
0;
0:
b100 P
b11110 ?
b100001110 >
b1 *
b1 4
b100 V
b100 #
b1100011 W
b1100011 $
b111111011 [
b10 I
b1110000100 A
b1110000100 &
b1110000100 Q
b100100011 M
b11 L
17
06
b10010 D
b10 F
b1001 .
b110 Z
b11110 N
b10 K
1)
13
#400000
0)
03
#405000
b10001101 O
b100 P
b111111111 >
b10 V
b10 #
b1101 W
b1101 $
b1101111011 [
b1101 *
b1101 4
b0 I
19
b100100011 A
b100100011 &
b100100011 Q
b100001110 M
b1 D
b1 F
b11111110 Z
b1100011 .
b0 K
1)
13
#410000
0)
03
#415000
b1100101 O
b111111011 >
0;
0:
1<
b100 P
b1000 ?
b1110110 *
b1110110 4
b0 V
b0 #
b10001101 W
b10001101 $
b100100011 [
b11110 I
09
b100001110 &
b100001110 Q
b100001110 A
b111111111 M
b1000 L
07
16
b1101 D
b11 F
b1101 .
1)
13
#420000
0)
03
#425000
1;
1:
b10010 O
0<
b1001 P
b110 ?
b1111000 >
1@
b11111110 V
b11111110 #
b1100101 W
b1100101 $
b100001110 [
b111101 *
b111101 4
b110 I
b111111111 &
b111111111 Q
b111111111 A
b111111011 M
b111 L
b1110110 D
b101 F
b10001101 .
b1000 N
1)
13
#430000
0)
03
#435000
1;
0:
b1 O
b11 P
b0 ?
b1000001 >
b11101101 *
b11101101 4
b110 V
b110 #
b10010 W
b10010 $
b111111111 [
b10 I
b1100000100 A
b1100000100 &
b1100000100 Q
b1111000 M
b100 L
15
06
b111101 D
b1100101 .
b1000 Z
b11100 N
b10 K
1)
13
#440000
0)
03
#445000
b11110001 >
b1101 O
0;
b101 P
b11100 ?
b10 V
b10 #
b1 W
b1 $
b1111111011 [
b10001100 *
b10001100 4
b1010000111 &
b1010000111 Q
b1010000111 A
b1000001 M
b10 L
05
17
b11101101 D
b110 F
b11111100 Z
b10010 .
b0 N
b0 K
1)
13
#450000
0)
03
#455000
0;
0:
b1110110 O
1<
b10 P
b10 ?
b110000100 >
0@
b11111001 *
b11111001 4
b1101 W
b1101 $
b1001111000 [
b11100 I
b1000001 A
b1000001 &
b1000001 Q
b11110001 M
b101 L
07
16
b10001100 D
b11 F
b1 .
b0 Z
b11010 N
b11110 K
1)
13
#460000
0)
03
#465000
1;
1:
b111101 O
b101 P
b11100 ?
b11111101 >
1@
b11111100 V
b11111100 #
b1110110 W
b1110110 $
b1000001 [
b11000110 *
b11000110 4
b11110001 &
b11110001 Q
b11110001 A
b110000100 M
b10 L
17
06
b11111001 D
b110 F
b11111010 Z
b1101 .
b0 N
1)
13
#470000
0)
03
#475000
b11101101 O
1;
1:
0<
b1000 P
b110 ?
b11101000 >
1@
b11000101 *
b11000101 4
b111101 W
b111101 $
b11110001 [
b10 I
b1101111011 A
b1101111011 &
b1101111011 Q
b11111101 M
b111 L
07
16
b11000110 D
b100 F
b1110110 .
b0 Z
b110 N
b10 K
1)
13
#480000
0)
03
#485000
0@
0:
b10001100 O
1<
b10 P
b0 ?
b101000011 >
b10 V
b10 #
b11101101 W
b11101101 $
b1110000100 [
b10101010 *
b10101010 4
b11100 I
b1000000010 &
b1000000010 Q
b1000000010 A
b11101000 M
b100 L
15
06
b11000101 D
b110 Z
b111101 .
b11010 N
b0 K
1)
13
#490000
0)
03
#495000
1@
1:
b11111001 O
b101 P
b11110 ?
b11001100 >
b11100101 *
b11100101 4
b11111100 V
b11111100 #
b10001100 W
b10001100 $
b1011111101 [
b1000010111 &
b1000010111 Q
b1000010111 A
b101000011 M
b11 L
05
17
b10101010 D
b11101101 .
b11111010 Z
b0 N
1)
13
#500000
0)
03
#505000
1;
0:
b11000110 O
0<
b111 P
b0 ?
b1001 >
b11111001 W
b11111001 $
b1011101000 [
b1110111 *
b1110111 4
b0 I
19
b1110111100 &
b1110111100 Q
b1110111100 A
b11001100 M
b100 L
15
07
b11100101 D
b101 F
b0 Z
b10001100 .
b100 N
b10 K
1)
13
#510000
0)
03
#515000
b10000111 >
b11000101 O
b101 P
b11100 ?
b10010 *
b10010 4
b0 V
b0 #
b11000110 W
b11000110 $
b1101000011 [
b1000110011 &
b1000110011 Q
b1000110011 A
b1001 M
b10 L
05
17
b1110111 D
b110 F
b11111001 .
b100 Z
b0 N
b0 K
1)
13
#520000
0)
03
#525000
b10101010 O
b111 P
b0 ?
b100001110 >
0@
b11000101 W
b11000101 $
b1011001100 [
b10001111 *
b10001111 4
b100 I
09
b1011110110 &
b1011110110 Q
b1011110110 A
b10000111 M
b100 L
15
07
b10010 D
b10 F
b0 Z
b11000110 .
b100 N
1)
13
#530000
0)
03
#535000
0;
b11100101 O
b101 P
b11110 ?
b101111 >
1@
b11110010 *
b11110010 4
b100 V
b100 #
b10101010 W
b10101010 $
b1000001001 [
b1001111000 &
b1001111000 Q
b1001111000 A
b100001110 M
b11 L
05
17
b10001111 D
b101 F
b11000101 .
b100 Z
b0 N
1)
13
#540000
0)
03
#545000
b1110111 O
1;
1:
b100 P
b10 ?
b100 >
b11100101 W
b11100101 $
b1010000111 [
b11001110 *
b11001110 4
b10 I
b100001110 A
b100001110 &
b100001110 Q
b101111 M
b101 L
07
16
b11110010 D
b0 Z
b10101010 .
b11110 N
1)
13
#550000
0)
03
#555000
b10000 >
0:
b10010 O
b100 P
b11010 ?
b11101000 *
b11101000 4
b10 V
b10 #
b1110111 W
b1110111 $
b100001110 [
b0 I
19
b1011010000 A
b1011010000 &
b1011010000 Q
b100 M
b1 L
17
06
b11001110 D
b11100101 .
b11111110 Z
1)
13
#560000
0)
03
#565000
b11110010 >
0;
b10001111 O
b1000 P
b0 V
b0 #
b10010 W
b10010 $
b1000101111 [
b11000101 *
b11000101 4
b110 I
09
b1011111011 &
b1011111011 Q
b1011111011 A
b10000 M
b11101000 D
b100 F
b1110111 .
b110 N
1)
13
#570000
0)
03
#575000
0@
0;
0:
b11110010 O
1<
b1 P
b10 ?
b101000011 >
b1011100 *
b1011100 4
b110 V
b110 #
b10001111 W
b10001111 $
b1000000100 [
b11110 I
b10000 A
b10000 &
b10000 Q
b11110010 M
b101 L
07
16
b11000101 D
b10010 .
b110 Z
b11000 N
b11110 K
1)
13
#580000
0)
03
#585000
b11001110 O
1@
1;
1:
b101 P
b11110 ?
b10011110 >
b11111110 V
b11111110 #
b11110010 W
b11110010 $
b10000 [
b10111101 *
b10111101 4
b11110010 &
b11110010 Q
b11110010 A
b101000011 M
b11 L
17
06
b1011100 D
b11111000 Z
b10001111 .
b0 N
1)
13
#590000
0)
03
#595000
b11101000 O
1;
1:
0<
b111 P
b10 ?
b11000001 >
b101101 *
b101101 4
b11001110 W
b11001110 $
b11110010 [
b10 I
b1110111100 A
b1110111100 &
b1110111100 Q
b10011110 M
b101 L
07
16
b10111101 D
b110 F
b11110010 .
b0 Z
b100 N
b10 K
1)
13
#600000
0)
03
#605000
0:
b100011011 >
b11000101 O
b100 P
b11110 ?
0@
b10 V
b10 #
b11101000 W
b11101000 $
b1101000011 [
b1100101 *
b1100101 4
b0 I
19
b1001100001 &
b1001100001 Q
b1001100001 A
b11000001 M
b11 L
17
06
b101101 D
b100 F
b100 Z
b11001110 .
b11110 N
b0 K
1)
13
#610000
0)
03
#615000
0;
b100100011 >
b1011100 O
b110 P
b0 ?
b1100011 *
b1100011 4
b0 V
b0 #
b11000101 W
b11000101 $
b1010011110 [
b10 I
09
b1000111110 &
b1000111110 Q
b1000111110 A
b100011011 M
b100 L
15
07
b1100101 D
b11101000 .
b11111110 Z
b10 N
1)
13
#620000
0)
03
#625000
b100100001 >
b10111101 O
b101 P
b11110 ?
b10 V
b10 #
b1011100 W
b1011100 $
b1011000001 [
b1010 *
b1010 4
b100011011 A
b100011011 &
b100011011 Q
b100100011 M
b11 L
05
17
b1100011 D
b10 Z
b11000101 .
b0 N
1)
13
#630000
0)
03
#635000
b101101 O
b100 P
b11100 ?
b100000110 >
b10000000 *
b10000000 4
b10111101 W
b10111101 $
b100011011 [
b0 I
19
b100100011 &
b100100011 Q
b100100011 A
b100100001 M
b10 L
b1010 D
b10 F
b1011100 .
b0 Z
b11110 N
1)
13
#640000
0)
03
#645000
1;
b1100101 O
1:
b110000000 >
1<
b11 P
b0 V
b0 #
b101101 W
b101101 $
b100100011 [
b100000 *
b100000 4
b11100 I
09
b100100001 &
b100100001 Q
b100100001 A
b100000110 M
b10000000 D
b1 F
b11111110 Z
b10111101 .
b11100 N
1)
13
#650000
0)
03
#655000
0;
b1100011 O
0:
b111100000 >
0<
b1000 P
b11010 ?
b10101010 *
b10101010 4
b11111100 V
b11111100 #
b1100101 W
b1100101 $
b100100001 [
b10 I
b1111111001 A
b1111111001 &
b1111111001 Q
b110000000 M
b1 L
b100000 D
b101101 .
b11111100 Z
b110 N
b10 K
1)
13
#660000
0)
03
#665000
1;
1:
b11001100 >
1@
b1010 O
1<
b10 P
b11110 ?
b10 V
b10 #
b1100011 W
b1100011 $
b1100000110 [
b10011101 *
b10011101 4
b11100 I
b110000000 A
b110000000 &
b110000000 Q
b111100000 M
b11 L
b10101010 D
b100 F
b110 Z
b1100101 .
b11010 N
b0 K
1)
13
#670000
0)
03
#675000
b10000000 O
1;
0:
0<
b111 P
b0 ?
b100001 >
b10010110 *
b10010110 4
b11111100 V
b11111100 #
b1010 W
b1010 $
b110000000 [
b0 I
19
b1100011111 A
b1100011111 &
b1100011111 Q
b11001100 M
b100 L
15
07
b10011101 D
b101 F
b1100011 .
b11111010 Z
b100 N
b10 K
1)
13
#680000
0)
03
#685000
b100000 O
b101 P
b11100 ?
b11011000 >
1@
b0 V
b0 #
b10000000 W
b10000000 $
b1111100000 [
b10011 *
b10011 4
b1000110011 &
b1000110011 Q
b1000110011 A
b100001 M
b10 L
05
17
b10010110 D
b100 F
b100 Z
b1010 .
b0 N
b0 K
1)
13
#690000
0)
03
#695000
b10101010 O
0@
b111 P
b0 ?
b111110001 >
b1101 *
b1101 4
b100000 W
b100000 $
b1011001100 [
b100 I
09
b1011011110 &
b1011011110 Q
b1011011110 A
b11011000 M
b100 L
15
07
b10011 D
b11 F
b10000000 .
b0 Z
b100 N
1)
13
#700000
0)
03
